{
  "$schema": "../../node_modules/ng-packagr/ng-package.schema.json",
  "dest": "../../dist/ngx-blockly",
  "lib": {
    "entryFile": "src/public_api.ts",
    "umdModuleIds": {
      "angular2-uuid": "angular2-uuid",
      "blockly/core": "Blockly",
      "blockly/msg/ab": "AB",
      "blockly/msg/ar": "AR",
      "blockly/msg/az": "AZ",
      "blockly/msg/ba": "BA",
      "blockly/msg/bcc": "BCC",
      "blockly/msg/be-tarask": "BE-TARASK",
      "blockly/msg/be": "BE",
      "blockly/msg/bg": "BG",
      "blockly/msg/bn": "BN",
      "blockly/msg/br": "BR",
      "blockly/msg/ca": "CA",
      "blockly/msg/da": "DA",
      "blockly/msg/de": "DE",
      "blockly/msg/diq": "DIQ",
      "blockly/msg/dty": "DTY",
      "blockly/msg/ee": "EE",
      "blockly/msg/el": "EL",
      "blockly/msg/en-gb": "EN-GB",
      "blockly/msg/en": "EN",
      "blockly/msg/eo": "EO",
      "blockly/msg/es": "ES",
      "blockly/msg/et": "ET",
      "blockly/msg/eu": "EU",
      "blockly/msg/fa": "FA",
      "blockly/msg/fi": "FI",
      "blockly/msg/fr": "FR",
      "blockly/msg/gl": "GL",
      "blockly/msg/gor": "GOR",
      "blockly/msg/ha": "HA",
      "blockly/msg/he": "HE",
      "blockly/msg/hi": "HI",
      "blockly/msg/hrx": "HRX",
      "blockly/msg/hu": "HU",
      "blockly/msg/hy": "HY",
      "blockly/msg/ia": "IA",
      "blockly/msg/id": "ID",
      "blockly/msg/ig": "IG",
      "blockly/msg/is": "IS",
      "blockly/msg/it": "IT",
      "blockly/msg/ja": "JA",
      "blockly/msg/kab": "KAB",
      "blockly/msg/kn": "KN",
      "blockly/msg/ko": "KO",
      "blockly/msg/lb": "LB",
      "blockly/msg/lki": "LKI",
      "blockly/msg/lo": "LO",
      "blockly/msg/lrc": "LRC",
      "blockly/msg/lt": "LT",
      "blockly/msg/lv": "LV",
      "blockly/msg/mk": "MV",
      "blockly/msg/mnw": "MNW",
      "blockly/msg/ms": "MS",
      "blockly/msg/nb": "NB",
      "blockly/msg/nl": "NL",
      "blockly/msg/oc": "OC",
      "blockly/msg/pl": "PL",
      "blockly/msg/pms": "PMS",
      "blockly/msg/pt-br": "PT-BR",
      "blockly/msg/pt": "PT",
      "blockly/msg/ro": "RO",
      "blockly/msg/ru": "RU",
      "blockly/msg/sc": "SC",
      "blockly/msg/sd": "SD",
      "blockly/msg/shn": "SHN",
      "blockly/msg/sk": "SK",
      "blockly/msg/skr-arab": "SKR-ARAB",
      "blockly/msg/sl": "SL",
      "blockly/msg/sq": "SQ",
      "blockly/msg/sr-latn": "SR-LATN",
      "blockly/msg/sr": "SR",
      "blockly/msg/sv": "SV",
      "blockly/msg/ta": "TA",
      "blockly/msg/tcy": "TCY",
      "blockly/msg/te": "TE",
      "blockly/msg/th": "TH",
      "blockly/msg/tl": "TL",
      "blockly/msg/tlh": "TLH",
      "blockly/msg/tr": "TR",
      "blockly/msg/ug-arab": "UG-ARAB",
      "blockly/msg/uk": "UK",
      "blockly/msg/ur": "UR",
      "blockly/msg/vi": "VI",
      "blockly/msg/xmf": "XMF",
      "blockly/msg/yo": "YO",
      "blockly/msg/zh-hans": "ZH-HANS",
      "blockly/msg/zh-hant": "ZH-HANT"
    }
  },
  "allowedNonPeerDependencies": [
    "angular2-uuid",
    "blockly"
  ]
}
